gconfigs/__init__.py
gconfigs/backends.py
gconfigs/gconfigs.py
gconfigs-0.1.5.dist-info/LICENSE
gconfigs-0.1.5.dist-info/WHEEL
gconfigs-0.1.5.dist-info/METADATA
gconfigs-0.1.5.dist-info/RECORD
