Metadata-Version: 2.1
Name: gconfigs
Version: 0.1.5
Summary: Config and Secret parser for your Python projects
Home-page: UNKNOWN
License: MIT
Author: Douglas Miranda
Author-email: douglascoding@gmail.com
Requires-Python: >=3.6,<4.0
Classifier: License :: OSI Approved :: MIT License
Classifier: Programming Language :: Python :: 3
Classifier: Programming Language :: Python :: 3.6
Classifier: Programming Language :: Python :: 3.7
